superduper_ibis/__init__.py
superduper_ibis/data_backend.py
superduper_ibis/db_helper.py
superduper_ibis/field_types.py
superduper_ibis/query.py
superduper_ibis/utils.py
superduper_ibis-0.5.4.dist-info/licenses/LICENSE
superduper_ibis-0.5.4.dist-info/METADATA
superduper_ibis-0.5.4.dist-info/WHEEL
superduper_ibis-0.5.4.dist-info/top_level.txt
superduper_ibis-0.5.4.dist-info/RECORD
