Metadata-Version: 2.4
Name: superduper_ibis
Version: 0.5.4
Summary: Superduper ibis is a plugin for ibis-framework that allows you to use Superduper as a backend for your ibis queries.
Maintainer-email: "superduper.io, Inc." <opensource@superduper.io>
License: 
Project-URL: homepage, https://superduper.io
Project-URL: documentation, https://docs.superduper.io/docs/intro
Project-URL: source, https://github.com/superduper-io/superduper
Keywords: databases,mongodb,data-science,machine-learning,mlops,vector-database,ai
Requires-Python: >=3.10
License-File: LICENSE
Requires-Dist: ibis-framework[sqlite]>=10.4.0
Requires-Dist: click
Requires-Dist: pandas
Requires-Dist: sqlalchemy
Provides-Extra: test
Dynamic: license-file
